example/__init__.py
rebyu/__init__.py
rebyu/base.py
rebyu/core.py
rebyu/version.py
rebyu/analysis/__init__.py
rebyu/analysis/embedding.py
rebyu/analysis/misc.py
rebyu/analysis/sentiment.py
rebyu/compose/__init__.py
rebyu/compose/ner.py
rebyu/compose/pos.py
rebyu/compose/vocab.py
rebyu/exception/__init__.py
rebyu/pipeline/__init__.py
rebyu/pipeline/base.py
rebyu/pipeline/pipeline.py
rebyu/pipeline/step.py
rebyu/preprocess/__init__.py
rebyu/preprocess/remove.py
rebyu/preprocess/scale.py
rebyu/preprocess/transform.py
rebyu/util/__init__.py
rebyu/util/dependency.py
rebyu/util/logger.py
rebyu/visual/__init__.py
rebyu-0.1.6.dist-info/LICENSE
rebyu-0.1.6.dist-info/METADATA
rebyu-0.1.6.dist-info/WHEEL
rebyu-0.1.6.dist-info/top_level.txt
rebyu-0.1.6.dist-info/zip-safe
rebyu-0.1.6.dist-info/RECORD
