Metadata-Version: 2.1
Name: rebyu
Version: 0.1.6
Summary: Review Analysis Made Easy
Home-page: https://github.com/abhishtagatya/rebyu
Author: Abhishta Gatya
Author-email: abhishtagatya@yahoo.com
Project-URL: Homepage, https://github.com/abhishtagatya/rebyu
Project-URL: Documentation, https://rebyu.readthedocs.io/
Project-URL: Change Log, https://github.com/abhishtagatya/rebyu/CHANGELOG.md
Classifier: Programming Language :: Python :: 3
Classifier: License :: OSI Approved :: Apache Software License
Classifier: Operating System :: OS Independent
Classifier: Topic :: Scientific/Engineering :: Artificial Intelligence
Classifier: Topic :: Scientific/Engineering :: Information Analysis
Classifier: Topic :: Scientific/Engineering :: Mathematics
Classifier: Topic :: Software Development :: Libraries :: Python Modules
Requires-Python: >=3.8
License-File: LICENSE
Requires-Dist: contractions
Requires-Dist: numpy
Requires-Dist: pandas
Requires-Dist: nltk (>=3.8)
Requires-Dist: textblob
Requires-Dist: transformers
Requires-Dist: xformers
Requires-Dist: loguru
